GGanalysis/__init__.py
GGanalysis/basic_models.py
GGanalysis/coupon_collection.py
GGanalysis/distribution_1d.py
GGanalysis/gacha_layers.py
GGanalysis/gacha_plot.py
GGanalysis/markov_method.py
GGanalysis/plot_tools.py
GGanalysis/ScoredItem/__init__.py
GGanalysis/ScoredItem/scored_item.py
GGanalysis/ScoredItem/scored_item_plot.py
GGanalysis/ScoredItem/scored_item_tools.py
GGanalysis/games/__init__.py
GGanalysis/games/alchemy_stars/__init__.py
GGanalysis/games/alchemy_stars/figure_plot.py
GGanalysis/games/alchemy_stars/gacha_model.py
GGanalysis/games/alchemy_stars/stationary_p.py
GGanalysis/games/arknights/__init__.py
GGanalysis/games/arknights/figure_plot.py
GGanalysis/games/arknights/gacha_model.py
GGanalysis/games/arknights/stationary_p.py
GGanalysis/games/azur_lane/__init__.py
GGanalysis/games/azur_lane/gacha_model.py
GGanalysis/games/blue_archive/__init__.py
GGanalysis/games/blue_archive/figure_plot.py
GGanalysis/games/blue_archive/gacha_model.py
GGanalysis/games/genshin_impact/__init__.py
GGanalysis/games/genshin_impact/artifact_data.py
GGanalysis/games/genshin_impact/artifact_model.py
GGanalysis/games/genshin_impact/figure_plot.py
GGanalysis/games/genshin_impact/gacha_model.py
GGanalysis/games/genshin_impact/get_both_EP_weapon.py
GGanalysis/games/genshin_impact/get_cost.py
GGanalysis/games/genshin_impact/predict_next_type.py
GGanalysis/games/genshin_impact/stationary_p.py
GGanalysis/games/girls_frontline2_exilium/__init__.py
GGanalysis/games/girls_frontline2_exilium/figure_plot.py
GGanalysis/games/girls_frontline2_exilium/gacha_model.py
GGanalysis/games/girls_frontline2_exilium/stationary_p.py
GGanalysis/games/honkai_impact_3rd_v2/__init__.py
GGanalysis/games/honkai_impact_3rd_v2/gacha_model.py
GGanalysis/games/honkai_star_rail/__init__.py
GGanalysis/games/honkai_star_rail/gacha_model.py
GGanalysis/games/honkai_star_rail/relic_data.py
GGanalysis/games/honkai_star_rail/relic_model.py
GGanalysis/games/honkai_star_rail/relic_sim.py
GGanalysis-0.4.2.dist-info/LICENSE
GGanalysis-0.4.2.dist-info/METADATA
GGanalysis-0.4.2.dist-info/WHEEL
GGanalysis-0.4.2.dist-info/top_level.txt
GGanalysis-0.4.2.dist-info/RECORD
