Metadata-Version: 2.1
Name: GGanalysis
Version: 0.4.2
Summary: A simple and efficient computing package for gacha game analysis.
Home-page: https://github.com/OneBST/GGanalysis
Author: OneBST
Author-email: onebst@foxmail.com
License: MIT
Requires-Python: >=3.9.0
License-File: LICENSE
Requires-Dist: numpy
Requires-Dist: scipy
Requires-Dist: matplotlib
